{"is_source_file": true, "format": "Python", "description": "This is a FastAPI application's main source file setting up the web API and CORS middleware, along with a health check endpoint.", "external_files": ["fastapi", "fastapi.middleware.cors"], "external_methods": ["FastAPI", "CORSMiddleware", "app.add_middleware", "@app.get"], "published": ["app"], "classes": [], "methods": [{"name": "health_check()", "description": "Endpoint responding with a health status message.", "scope": "", "scopeKind": ""}], "calls": ["FastAPI()", "app.add_middleware()", "CORSMiddleware()", "@app.get()"], "search-terms": ["FastAPI", "CORS middleware", "main.py", "health check endpoint", "API setup"], "state": 2, "file_id": 2, "knowledge_revision": 9, "git_revision": "c1a03cd867aca07af25d8004449fe88b78152c1a", "ctags": [{"_type": "tag", "name": "app", "path": "/home/kavia/workspace/code-generation/minimalist-todo-list-51982-51991/todo_backend/src/api/main.py", "pattern": "/^app = FastAPI()$/", "language": "Python", "kind": "variable"}, {"_type": "tag", "name": "health_check", "path": "/home/kavia/workspace/code-generation/minimalist-todo-list-51982-51991/todo_backend/src/api/main.py", "pattern": "/^def health_check():$/", "language": "Python", "kind": "function", "signature": "()"}], "hash": "58352bf5f133908bab16643199aa483d", "format-version": 4, "code-base-name": "todo_backend", "filename": "todo_backend/src/api/main.py", "fields": [{"name": "app = FastAPI()", "scope": "", "scopeKind": "", "description": "unavailable"}], "revision_history": [{"9": "c1a03cd867aca07af25d8004449fe88b78152c1a"}]}